README.rst
setup.py
libsmev/__init__.py
libsmev/attachments.py
libsmev/helpers.py
libsmev/namespaces.py
libsmev/signer.py
libsmev/skeleton.py
libsmev/test_libsmev.py
m3_libsmev.egg-info/PKG-INFO
m3_libsmev.egg-info/SOURCES.txt
m3_libsmev.egg-info/dependency_links.txt
m3_libsmev.egg-info/requires.txt
m3_libsmev.egg-info/top_level.txt