Metadata-Version: 1.1
Name: m3-libsmev
Version: 0.1.6.4
Summary: Library of low-level helpers that make integration with SMEV somewhat less painful
Home-page: UNKNOWN
Author: Borisov Kirill
Author-email: borisov@bars-open.ru
License: MIT
Keywords: smev m3 bars
Platform: UNKNOWN
Classifier: Intended Audience :: Developers
Classifier: Environment :: Web Environment
Classifier: Natural Language :: Russian
Classifier: Natural Language :: English
Classifier: Operating System :: OS Independent
Classifier: Programming Language :: Python
Classifier: License :: OSI Approved :: MIT License
Classifier: Development Status :: 5 - Production/Stable
